setup.py
OhMyChat_API/Get_API.py
OhMyChat_API/__init__.py
Zxy_Private.egg-info/PKG-INFO
Zxy_Private.egg-info/SOURCES.txt
Zxy_Private.egg-info/dependency_links.txt
Zxy_Private.egg-info/top_level.txt