Metadata-Version: 2.1
Name: Zxy-Private
Version: 0.0.2
Summary: 已更新
Home-page: https://github.com/
Author: AnQing
License: UNKNOWN
Platform: UNKNOWN
Classifier: Programming Language :: Python :: 3
Classifier: License :: OSI Approved :: MIT License
Classifier: Operating System :: OS Independent
